[{"id":2,"titulo":"My Melody Adventures","anolanzamento":1975,"ambientacion":"Bosque encantado","publico":"Infantil","personaxes":[{"nome":"My Melody","tipo":"Protagonista"},{"nome":"Flat","tipo":"Amigo"},{"nome":"Kuromi","tipo":"Antagonista"}]},{"id":1,"titulo":"Hello Kitty Classic","anolanzamento":1974,"ambientacion":"Londres","publico":"Infantil","personaxes":[{"nome":"Hello Kitty","tipo":"Protagonista"},{"nome":"Dear Daniel","tipo":"Amigo"},{"nome":"Mimmy","tipo":"Irmá xemelga"}]},{"id":3,"titulo":"Kuromi Chaos","anolanzamento":2005,"ambientacion":"Cidade alternativa","publico":"Xuventude","personaxes":[{"nome":"Kuromi","tipo":"Protagonista"},{"nome":"Baku","tipo":"Compañeiro"}]},{"id":4,"titulo":"Cinnamoroll Skies","anolanzamento":2002,"ambientacion":"Ceos e nubes","publico":"Todos os públicos","personaxes":[{"nome":"Cinnamoroll","tipo":"Protagonista"},{"nome":"Mocha","tipo":"Amiga"},{"nome":"Chiffon","tipo":"Amiga"}]},{"id":5,"titulo":"Hellow Kitty \u0026 Friends","anolanzamento":2010,"ambientacion":"Sanrio Town","publico":"Todos os publicos","personaxes":[{"nome":"Hellow Kity","tipo":"protagonista"},{"nome":"My Melody","tipo":"amiga"},{"nome":"Kuromi","tipo":"rival"},{"nome":"Cinnamoroll","tipo":"amigo"}]},{"id":6,"titulo":"Hellow Kitty \u0026 Friends","anolanzamento":2010,"ambientacion":"Sanrio Town","publico":"Todos os publicos","personaxes":[{"nome":"Hellow Kity","tipo":"protagonista"},{"nome":"My Melody","tipo":"amiga"},{"nome":"Kuromi","tipo":"rival"},{"nome":"Cinnamoroll","tipo":"amigo"}]},{"id":7,"titulo":"Hellow Kitty \u0026 Friends","anolanzamento":2010,"ambientacion":"Sanrio Town","publico":"Todos os publicos","personaxes":[{"nome":"Hellow Kity","tipo":"protagonista"},{"nome":"My Melody","tipo":"amiga"},{"nome":"Kuromi","tipo":"rival"},{"nome":"Cinnamoroll","tipo":"amigo"}]},{"id":8,"titulo":"Hellow Kitty \u0026 Friends","anolanzamento":2010,"ambientacion":"Sanrio Town","publico":"Todos os publicos","personaxes":[{"nome":"Hellow Kity","tipo":"protagonista"},{"nome":"My Melody","tipo":"amiga"},{"nome":"Kuromi","tipo":"rival"},{"nome":"Cinnamoroll","tipo":"amigo"}]}]